odoo/addons/partner_aging/README.rst
odoo/addons/partner_aging/__init__.py
odoo/addons/partner_aging/__manifest__.py
odoo/addons/partner_aging/i18n/es.po
odoo/addons/partner_aging/i18n/fr.po
odoo/addons/partner_aging/i18n/hr.po
odoo/addons/partner_aging/i18n/partner_aging.pot
odoo/addons/partner_aging/i18n/pt.po
odoo/addons/partner_aging/i18n/pt_BR.po
odoo/addons/partner_aging/readme/CONTRIBUTORS.rst
odoo/addons/partner_aging/readme/CREDITS.rst
odoo/addons/partner_aging/readme/DESCRIPTION.rst
odoo/addons/partner_aging/readme/USAGE.rst
odoo/addons/partner_aging/security/ir.model.access.csv
odoo/addons/partner_aging/static/description/icon.png
odoo/addons/partner_aging/static/description/index.html
odoo/addons/partner_aging/tests/__init__.py
odoo/addons/partner_aging/tests/test_partner_aging.py
odoo/addons/partner_aging/wizard/__init__.py
odoo/addons/partner_aging/wizard/res_partner_aging_customer.py
odoo/addons/partner_aging/wizard/res_partner_aging_customer.xml
odoo/addons/partner_aging/wizard/res_partner_aging_date.py
odoo/addons/partner_aging/wizard/res_partner_aging_supplier.py
odoo/addons/partner_aging/wizard/res_partner_aging_supplier.xml
odoo12_addon_partner_aging-12.0.1.0.0.99.dev20.dist-info/METADATA
odoo12_addon_partner_aging-12.0.1.0.0.99.dev20.dist-info/WHEEL
odoo12_addon_partner_aging-12.0.1.0.0.99.dev20.dist-info/top_level.txt
odoo12_addon_partner_aging-12.0.1.0.0.99.dev20.dist-info/RECORD
